FoxDotChord/__init__.py
FoxDotChord/_chord.py
FoxDotChord/_notes.py
FoxDotChord/_pattern.py
FoxDotChord/_require.py
FoxDotChord/_timevar.py
foxdotchord-0.0.12b1.dist-info/LICENSE
foxdotchord-0.0.12b1.dist-info/METADATA
foxdotchord-0.0.12b1.dist-info/WHEEL
foxdotchord-0.0.12b1.dist-info/RECORD
