Metadata-Version: 2.3
Name: FoxDotChord
Version: 0.0.12b1
Summary: Chords for use in renardo or FoxDot
License: GPL-3.0-or-later
Keywords: FoxDot,foxdot,renardo,chord,algorave,live-coding,music,patterns
Author: taconi
Author-email: igor.taconi@protonmail.com
Maintainer: taconi
Maintainer-email: igor.taconi@protonmail.com
Requires-Python: >=3.9,<4.0
Classifier: Development Status :: 2 - Pre-Alpha
Classifier: Intended Audience :: End Users/Desktop
Classifier: Intended Audience :: Science/Research
Classifier: License :: OSI Approved
Classifier: License :: OSI Approved :: GNU General Public License v3 or later (GPLv3+)
Classifier: Programming Language :: Python :: 3.9
Classifier: Programming Language :: Python :: 3.10
Classifier: Programming Language :: Python :: 3.11
Classifier: Programming Language :: Python :: 3.12
Classifier: Programming Language :: Python :: 3.13
Classifier: Topic :: Software Development :: Libraries :: Application Frameworks
Classifier: Topic :: Utilities
Classifier: Topic :: Artistic Software
Classifier: Topic :: Multimedia :: Sound/Audio
Project-URL: Contributor Guide, https://foxdotchord.readthedocs.io/contributing
Project-URL: Changelog, https://foxdotchord.readthedocs.io/changelog/
Project-URL: Documentation, https://foxdotchord.readthedocs.io
Project-URL: Homepage, https://codeberg.org/taconi/FoxDotChord
Project-URL: Issues, https://codeberg.org/taconi/FoxDotChord/issues
Project-URL: Repository, https://codeberg.org/taconi/FoxDotChord
